grist_jupyterlab_widget/__init__.py
grist_jupyterlab_widget/_version.py
grist_jupyterlab_widget-0.7.0.data/data/share/jupyter/labextensions/grist-widget/package.json
grist_jupyterlab_widget-0.7.0.data/data/share/jupyter/labextensions/grist-widget/static/292.a196a79f096b9914df2d.js
grist_jupyterlab_widget-0.7.0.data/data/share/jupyter/labextensions/grist-widget/static/747.b103248917ce4560b62f.js
grist_jupyterlab_widget-0.7.0.data/data/share/jupyter/labextensions/grist-widget/static/870.cc5e6191ab9beb02306e.js
grist_jupyterlab_widget-0.7.0.data/data/share/jupyter/labextensions/grist-widget/static/870.cc5e6191ab9beb02306e.js.LICENSE.txt
grist_jupyterlab_widget-0.7.0.data/data/share/jupyter/labextensions/grist-widget/static/remoteEntry.2d9f8bf4ad0ec9dc2b4a.js
grist_jupyterlab_widget-0.7.0.data/data/share/jupyter/labextensions/grist-widget/static/style.js
grist_jupyterlab_widget-0.7.0.data/data/share/jupyter/labextensions/grist-widget/static/third-party-licenses.json
grist_jupyterlab_widget-0.7.0.data/data/share/jupyter/labextensions/grist-widget/install.json
grist_jupyterlab_widget-0.7.0.dist-info/METADATA
grist_jupyterlab_widget-0.7.0.dist-info/WHEEL
grist_jupyterlab_widget-0.7.0.dist-info/licenses/LICENSE
grist_jupyterlab_widget-0.7.0.dist-info/RECORD
